jsonvalidator/__init__.py
jsonvalidator/jsonvalidator.py
jsonvalidator/test_jsonvalidator.py
python_jsonvalidator-0.0.2.dist-info/METADATA
python_jsonvalidator-0.0.2.dist-info/WHEEL
python_jsonvalidator-0.0.2.dist-info/top_level.txt
python_jsonvalidator-0.0.2.dist-info/RECORD
