Metadata-Version: 2.1
Name: python-jsonvalidator
Version: 0.0.2
Summary: This package helps you validate     dictionaries against a defined schema     
Home-page: https://github.com/murungakibaara/jsonvalidator
Author: Murunga Kibaara
Author-email: matatamatata3@gmail.com
License: UNKNOWN
Platform: UNKNOWN
Classifier: Programming Language :: Python :: 3
Classifier: License :: OSI Approved :: MIT License
Classifier: Operating System :: OS Independent
